iqs_jupyter/__init__.py
iqs_jupyter/about.py
iqs_jupyter/abstract_widgets.py
iqs_jupyter/analysis_extensions.py
iqs_jupyter/api_composition.py
iqs_jupyter/authentication.py
iqs_jupyter/config_defaults.py
iqs_jupyter/core_extensions.py
iqs_jupyter/helpers.py
iqs_jupyter/mms_direct_extensions.py
iqs_jupyter/mms_extensions.py
iqs_jupyter/tool_extension_point.py
iqs_jupyter/twc_extensions.py
iqs_jupyter/twc_osmc_extensions.py
incqueryserver_jupyter-0.24.0.dist-info/LICENSE
incqueryserver_jupyter-0.24.0.dist-info/METADATA
incqueryserver_jupyter-0.24.0.dist-info/WHEEL
incqueryserver_jupyter-0.24.0.dist-info/top_level.txt
incqueryserver_jupyter-0.24.0.dist-info/RECORD
