Metadata-Version: 2.1
Name: incqueryserver-jupyter
Version: 0.24.0
Summary: IncQuery Server Client Extensions for Jupyter and Python
Home-page: https://github.com/IncQueryLabs/incquery-server-jupyter
Author: Gábor Bergmann
Author-email: gabor.bergmann@incquerylabs.com
License: UNKNOWN
Platform: UNKNOWN
Classifier: Programming Language :: Python :: 3
Classifier: License :: OSI Approved :: Apache Software License
Classifier: Operating System :: OS Independent
License-File: LICENSE
Requires-Dist: incqueryserver-api-python-client (==0.24.0)
Requires-Dist: mms-python-client
Requires-Dist: ipywidgets
